{
	"books": [
		{
			"author": "by James Patterson and James O. Born",
			"description": "The 12th book in the Michael Bennett series. A serial-killing spree might impact national security.",
			"imageSrc": "https://storage.googleapis.com/du-prd/books/images/9780316420334.jpg",
			"name": "BLINDSIDE",
			"publisher": "Little, Brown",
			"rank": 1
		},
		{
			"author": "by Steve Berry",
			"description": "The 15th book in the Cotton Malone series. The balance of power in Europe is imperiled.",
			"imageSrc": "https://storage.googleapis.com/du-prd/books/images/9781250140319.jpg",
			"name": "THE WARSAW PROTOCOL",
			"publisher": "Minotaur",
			"rank": 2
		},
		{
			"author": "by Jeanine Cummins",
			"description": "A bookseller flees Mexico for the United States with her son while pursued by the head of a drug cartel.",
			"imageSrc": "https://storage.googleapis.com/du-prd/books/images/9781250209764.jpg",
			"name": "AMERICAN DIRT",
			"publisher": "Flatiron",
			"rank": 3
		},
		{
			"author": "by Delia Owens",
			"description": "In a quiet town on the North Carolina coast in 1969, a young woman who survived alone in the marsh becomes a murder suspect.",
			"imageSrc": "https://storage.googleapis.com/du-prd/books/images/9780735219090.jpg",
			"name": "WHERE THE CRAWDADS SING",
			"publisher": "Putnam",
			"rank": 4
		},
		{
			"author": "by Celeste Ng",
			"description": "An artist upends a quiet town outside Cleveland.",
			"imageSrc": "https://storage.googleapis.com/du-prd/books/images/9780735224308.jpg",
			"name": "LITTLE FIRES EVERYWHERE",
			"publisher": "Penguin Press",
			"rank": 5
		},
		{
			"author": "by Joanne Fluke",
			"description": "The bakery owner Hannah Swensen\u2019s sister\u2019s boyfriend is accused of murder.",
			"imageSrc": "https://storage.googleapis.com/du-prd/books/images/9781496718891.jpg",
			"name": "COCONUT LAYER CAKE MURDER",
			"publisher": "Kensington",
			"rank": 6
		},
		{
			"author": "by Andrzej Sapkowski",
			"description": "Linked stories follow the exploits of Geralt of Rivia, a monster-slaying mercenary.",
			"imageSrc": "https://storage.googleapis.com/du-prd/books/images/9780316438964.jpg",
			"name": "THE LAST WISH",
			"publisher": "Orbit",
			"rank": 7
		},
		{
			"author": "by Alex Michaelides",
			"description": "Theo Faber looks into the mystery of a famous painter who stops speaking after shooting her husband.",
			"imageSrc": "https://storage.googleapis.com/du-prd/books/images/9781250301697.jpg",
			"name": "THE SILENT PATIENT",
			"publisher": "Celadon",
			"rank": 8
		},
		{
			"author": "by Ann Patchett",
			"description": "A sibling relationship is impacted when the family goes from poverty to wealth and back again over the course of many decades.",
			"imageSrc": "https://storage.googleapis.com/du-prd/books/images/9780062963673.jpg",
			"name": "THE DUTCH HOUSE",
			"publisher": "Harper",
			"rank": 9
		},
		{
			"author": "by Jojo Moyes",
			"description": "In Depression-era Kentucky, five women refuse to be cowed by men or convention as they deliver books.",
			"imageSrc": "https://storage.googleapis.com/du-prd/books/images/9780399562501.jpg",
			"name": "THE GIVER OF STARS",
			"publisher": "Pamela Dorman/Viking",
			"rank": 10
		},
		{
			"author": "by J.D. Robb",
			"description": "The 50th book of the In Death series. Eve Dallas seeks the sender of packages that give off toxic airborne fumes.",
			"imageSrc": "https://storage.googleapis.com/du-prd/books/images/9781250207203.jpg",
			"name": "GOLDEN IN DEATH",
			"publisher": "St. Martin's",
			"rank": 11
		},
		{
			"author": "by Heather Morris",
			"description": "A concentration camp detainee tasked with permanently marking fellow prisoners falls in love with one of them.",
			"imageSrc": "https://storage.googleapis.com/du-prd/books/images/9780062797155.jpg",
			"name": "THE TATTOOIST OF AUSCHWITZ",
			"publisher": "Harper",
			"rank": 12
		},
		{
			"author": "by Kiley Reid",
			"description": "Tumult ensues when Alix Chamberlain\u2019s babysitter is mistakenly accused of kidnapping her charge.",
			"imageSrc": "https://storage.googleapis.com/du-prd/books/images/9780525541905.jpg",
			"name": "SUCH A FUN AGE",
			"publisher": "Putnam",
			"rank": 13
		},
		{
			"author": "by Stephen King",
			"description": "A detective investigates a seemingly wholesome member of the community when an 11-year-old boy\u2019s body is found.",
			"imageSrc": "https://storage.googleapis.com/du-prd/books/images/9781501180989.jpg",
			"name": "THE OUTSIDER",
			"publisher": "Scribner",
			"rank": 14
		},
		{
			"author": "by Lisa Kleypas",
			"description": "The sixth book in the Ravenels series. Cassandra teaches a railway magnate a lesson.",
			"imageSrc": "https://storage.googleapis.com/du-prd/books/images/9780062371959.jpg",
			"name": "CHASING CASSANDRA",
			"publisher": "Avon",
			"rank": 15
		}
	]
}